[
  { "label": "2015", "nba": 4600000, "epl": 3000000 },
  { "label": "2016", "nba": 5000000, "epl": 3300000 },
  { "label": "2017", "nba": 6200000, "epl": 3500000 },
  { "label": "2018", "nba": 6400000, "epl": 3700000 },
  { "label": "2019", "nba": 7700000, "epl": 3900000 },
  { "label": "2020", "nba": 7900000, "epl": 3800000 },
  { "label": "2021", "nba": 7500000, "epl": 3600000 },
  { "label": "2022", "nba": 8500000, "epl": 4200000 },
  { "label": "2023", "nba": 9600000, "epl": 4800000 },
  { "label": "2024", "nba": 10300000, "epl": 5200000 },
  { "label": "2025", "nba": 10800000, "epl": 5600000 }
]